humble_tools/__init__.py
humble_tools/cli.py
humble_tools_make/__init__.py
humble_tools-0.2.dist-info/METADATA
humble_tools-0.2.dist-info/WHEEL
humble_tools-0.2.dist-info/entry_points.txt
humble_tools-0.2.dist-info/top_level.txt
humble_tools-0.2.dist-info/zip-safe
humble_tools-0.2.dist-info/RECORD
